livedanmaku/__init__.py
livedanmaku/client.py
livedanmaku/danmaku.py
livedanmaku/monitor.py
livedanmaku-0.0.6.dist-info/LICENSE
livedanmaku-0.0.6.dist-info/METADATA
livedanmaku-0.0.6.dist-info/WHEEL
livedanmaku-0.0.6.dist-info/top_level.txt
livedanmaku-0.0.6.dist-info/RECORD
