Metadata-Version: 2.1
Name: livedanmaku
Version: 0.0.6
Summary: A python library for resolving Bilibili Danmaku with Flask-style API.
Home-page: https://github.com/MerlynAllen/bilibili_danmaku/
Author: Merlyn Allen
Author-email: xiaorui2001@outlook.com
Project-URL: Bug Tracker, https://github.com/MerlynAllen/bilibili_danmaku/issues
Project-URL: Source Code, https://github.com/MerlynAllen/bilibili_danmaku/
Classifier: Programming Language :: Python :: 3
Classifier: License :: OSI Approved :: MIT License
Classifier: Operating System :: OS Independent
Requires-Python: >=3.6
License-File: LICENSE
Requires-Dist: aioconsole (==0.3.3)
Requires-Dist: aiohttp (==3.8.1)
Requires-Dist: brotli (==1.0.9)
Requires-Dist: brotlipy (==0.7.0)
Requires-Dist: requests (==2.26.0)
